daml_dit_if/__init__.py
daml_dit_if/api/__init__.py
daml_dit_if/api/common.py
daml_dit_if/main/__init__.py
daml_dit_if/main/__main__.py
daml_dit_if/main/auth_accessors.py
daml_dit_if/main/auth_handler.py
daml_dit_if/main/common.py
daml_dit_if/main/config.py
daml_dit_if/main/integration_context.py
daml_dit_if/main/integration_deferral_queue.py
daml_dit_if/main/integration_ledger_context.py
daml_dit_if/main/integration_queue_context.py
daml_dit_if/main/integration_time_context.py
daml_dit_if/main/integration_webhook_context.py
daml_dit_if/main/jwt.py
daml_dit_if/main/log.py
daml_dit_if/main/main.py
daml_dit_if/main/package_metadata_introspection.py
daml_dit_if/main/util.py
daml_dit_if/main/web.py
daml_dit_if/py.typed
daml_dit_if-0.7.1.dist-info/LICENSE
daml_dit_if-0.7.1.dist-info/METADATA
daml_dit_if-0.7.1.dist-info/WHEEL
daml_dit_if-0.7.1.dist-info/RECORD
