Metadata-Version: 2.1
Name: daml-dit-if
Version: 0.7.1
Summary: Daml Hub Integration Framework
Home-page: https://github.com/digital-asset/daml-dit-if
Keywords: daml,blockchain,dlt,distributed ledger,digital asset
Author: Daml Hub Team
Author-email: no-reply@digitalasset.com
Requires-Python: >=3.8,<4.0
Classifier: Programming Language :: Python :: 3
Classifier: Programming Language :: Python :: 3.8
Classifier: Programming Language :: Python :: 3.9
Classifier: Programming Language :: Python :: 3.10
Classifier: Programming Language :: Python :: 3.11
Classifier: Programming Language :: Python :: 3.12
Provides-Extra: develop
Requires-Dist: aiohttp
Requires-Dist: dacite
Requires-Dist: daml-dit-api
Requires-Dist: dazl (>=7,<8)
Requires-Dist: idna
Requires-Dist: jwcrypto
Requires-Dist: prometheus-client
Requires-Dist: pyyaml
Project-URL: Repository, https://github.com/digital-asset/daml-dit-if
